{
  "item": [
    {
      "id": "846de522-6620-4631-8fe6-86d34ce0299c",
      "name": "Organization Exports",
      "description": {
        "content": "Export organization data in JSON format.",
        "type": "text/plain"
      },
      "item": [
        {
          "id": "635b99a8-488b-4036-a1aa-ba2359ed0a84",
          "name": "Asana Create an organization export request",
          "request": {
            "name": "Asana Create an organization export request",
            "description": {
              "content": "Creates an organization export request for the given organization.",
              "type": "text/plain"
            },
            "url": {
              "path": [
                "organization_exports"
              ],
              "host": [
                "{{baseUrl}}"
              ],
              "query": [],
              "variable": []
            },
            "header": [
              {
                "key": "Content-Type",
                "value": "application/json"
              },
              {
                "key": "Accept",
                "value": "application/json"
              }
            ],
            "method": "POST",
            "auth": null,
            "body": {
              "mode": "raw",
              "raw": "{\n  \"data\": {\n    \"organization\": \"<string>\"\n  }\n}",
              "options": {
                "raw": {
                  "language": "json"
                }
              }
            }
          },
          "response": [
            {
              "id": "59c8e587-3043-4c96-a0da-c02a5f7bd281",
              "name": "Successfully created an organization export request.",
              "originalRequest": {
                "url": {
                  "path": [
                    "organization_exports"
                  ],
                  "host": [
                    "{{baseUrl}}"
                  ],
                  "query": [],
                  "variable": []
                },
                "header": [
                  {
                    "description": {
                      "content": "Added as a part of security scheme: bearer",
                      "type": "text/plain"
                    },
                    "key": "Authorization",
                    "value": "Bearer <token>"
                  },
                  {
                    "key": "Accept",
                    "value": "application/json"
                  }
                ],
                "method": "POST",
                "body": {
                  "mode": "raw",
                  "raw": "{\n  \"data\": {\n    \"organization\": \"1331\"\n  }\n}",
                  "options": {
                    "raw": {
                      "language": "json"
                    }
                  }
                }
              },
              "status": "Created",
              "code": 201,
              "header": [
                {
                  "key": "Content-Type",
                  "value": "application/json"
                }
              ],
              "body": "{\n  \"data\": {\n    \"gid\": \"12345\",\n    \"resource_type\": \"organization_export\",\n    \"state\": \"started\",\n    \"download_url\": \"http://aMaULLYfowNtjOpaaOMuyPBhOwLUfXrT.jrokJb+Kb.xsCiuoUOb..lxhYXc7k\",\n    \"organization\": {\n      \"gid\": \"string\",\n      \"resource_type\": \"string\",\n      \"name\": \"string\"\n    },\n    \"created_at\": \"1966-11-15T00:09:45.907Z\"\n  }\n}",
              "cookie": [],
              "_postman_previewlanguage": "json"
            },
            {
              "id": "5888497c-d24c-41c0-8cce-28f40dd518ea",
              "name": "Bad request.",
              "originalRequest": {
                "url": {
                  "path": [
                    "organization_exports"
                  ],
                  "host": [
                    "{{baseUrl}}"
                  ],
                  "query": [],
                  "variable": []
                },
                "header": [
                  {
                    "description": {
                      "content": "Added as a part of security scheme: bearer",
                      "type": "text/plain"
                    },
                    "key": "Authorization",
                    "value": "Bearer <token>"
                  }
                ],
                "method": "POST",
                "body": {
                  "mode": "raw",
                  "raw": "{\n  \"data\": {\n    \"organization\": \"1331\"\n  }\n}",
                  "options": {
                    "raw": {
                      "language": "json"
                    }
                  }
                }
              },
              "status": "Bad Request",
              "code": 400,
              "header": [
                {
                  "key": "Content-Type",
                  "value": "text/plain"
                }
              ],
              "body": "",
              "cookie": [],
              "_postman_previewlanguage": "text"
            },
            {
              "id": "328f9e25-92fc-4674-b2ae-b3b2c0acba2c",
              "name": "Unauthorized.",
              "originalRequest": {
                "url": {
                  "path": [
                    "organization_exports"
                  ],
                  "host": [
                    "{{baseUrl}}"
                  ],
                  "query": [],
                  "variable": []
                },
                "header": [
                  {
                    "description": {
                      "content": "Added as a part of security scheme: bearer",
                      "type": "text/plain"
                    },
                    "key": "Authorization",
                    "value": "Bearer <token>"
                  }
                ],
                "method": "POST",
                "body": {
                  "mode": "raw",
                  "raw": "{\n  \"data\": {\n    \"organization\": \"1331\"\n  }\n}",
                  "options": {
                    "raw": {
                      "language": "json"
                    }
                  }
                }
              },
              "status": "Unauthorized",
              "code": 401,
              "header": [
                {
                  "key": "Content-Type",
                  "value": "text/plain"
                }
              ],
              "body": "",
              "cookie": [],
              "_postman_previewlanguage": "text"
            },
            {
              "id": "8a336cd6-c3ee-4139-9a9f-9b91fbadc147",
              "name": "Forbidden.",
              "originalRequest": {
                "url": {
                  "path": [
                    "organization_exports"
                  ],
                  "host": [
                    "{{baseUrl}}"
                  ],
                  "query": [],
                  "variable": []
                },
                "header": [
                  {
                    "description": {
                      "content": "Added as a part of security scheme: bearer",
                      "type": "text/plain"
                    },
                    "key": "Authorization",
                    "value": "Bearer <token>"
                  }
                ],
                "method": "POST",
                "body": {
                  "mode": "raw",
                  "raw": "{\n  \"data\": {\n    \"organization\": \"1331\"\n  }\n}",
                  "options": {
                    "raw": {
                      "language": "json"
                    }
                  }
                }
              },
              "status": "Forbidden",
              "code": 403,
              "header": [
                {
                  "key": "Content-Type",
                  "value": "text/plain"
                }
              ],
              "body": "",
              "cookie": [],
              "_postman_previewlanguage": "text"
            },
            {
              "id": "52c968ef-9a90-469e-97a3-c36c32d10858",
              "name": "Internal server error.",
              "originalRequest": {
                "url": {
                  "path": [
                    "organization_exports"
                  ],
                  "host": [
                    "{{baseUrl}}"
                  ],
                  "query": [],
                  "variable": []
                },
                "header": [
                  {
                    "description": {
                      "content": "Added as a part of security scheme: bearer",
                      "type": "text/plain"
                    },
                    "key": "Authorization",
                    "value": "Bearer <token>"
                  }
                ],
                "method": "POST",
                "body": {
                  "mode": "raw",
                  "raw": "{\n  \"data\": {\n    \"organization\": \"1331\"\n  }\n}",
                  "options": {
                    "raw": {
                      "language": "json"
                    }
                  }
                }
              },
              "status": "Internal Server Error",
              "code": 500,
              "header": [
                {
                  "key": "Content-Type",
                  "value": "text/plain"
                }
              ],
              "body": "",
              "cookie": [],
              "_postman_previewlanguage": "text"
            }
          ],
          "event": [],
          "protocolProfileBehavior": {
            "disableBodyPruning": true
          }
        },
        {
          "id": "c4639a72-d3ca-41a8-9b66-97754921fb06",
          "name": "Asana Get details on an org export request",
          "request": {
            "name": "Asana Get details on an org export request",
            "description": {
              "content": "Returns details of a previously-requested organization export.",
              "type": "text/plain"
            },
            "url": {
              "path": [
                "organization_exports",
                ":organization_export_gid"
              ],
              "host": [
                "{{baseUrl}}"
              ],
              "query": [],
              "variable": [
                {
                  "disabled": false,
                  "type": "any",
                  "value": "<string>",
                  "key": "organization_export_gid",
                  "description": "(Required) "
                }
              ]
            },
            "header": [
              {
                "key": "Accept",
                "value": "application/json"
              }
            ],
            "method": "GET",
            "auth": null
          },
          "response": [
            {
              "id": "37375db0-5a45-459b-92a0-cd82c47261ed",
              "name": "Successfully retrieved the requested organization export.",
              "originalRequest": {
                "url": {
                  "path": [
                    "organization_exports",
                    ":organization_export_gid"
                  ],
                  "host": [
                    "{{baseUrl}}"
                  ],
                  "query": [],
                  "variable": [
                    {
                      "disabled": false,
                      "type": "any",
                      "value": "<string>",
                      "key": "organization_export_gid",
                      "description": "(Required) "
                    }
                  ]
                },
                "header": [
                  {
                    "description": {
                      "content": "Added as a part of security scheme: bearer",
                      "type": "text/plain"
                    },
                    "key": "Authorization",
                    "value": "Bearer <token>"
                  },
                  {
                    "key": "Accept",
                    "value": "application/json"
                  }
                ],
                "method": "GET",
                "body": {}
              },
              "status": "OK",
              "code": 200,
              "header": [
                {
                  "key": "Content-Type",
                  "value": "application/json"
                }
              ],
              "body": "{\n  \"data\": {\n    \"gid\": \"12345\",\n    \"resource_type\": \"organization_export\",\n    \"state\": \"started\",\n    \"download_url\": \"http://aMaULLYfowNtjOpaaOMuyPBhOwLUfXrT.jrokJb+Kb.xsCiuoUOb..lxhYXc7k\",\n    \"organization\": {\n      \"gid\": \"string\",\n      \"resource_type\": \"string\",\n      \"name\": \"string\"\n    },\n    \"created_at\": \"1966-11-15T00:09:45.907Z\"\n  }\n}",
              "cookie": [],
              "_postman_previewlanguage": "json"
            },
            {
              "id": "82fbd1c1-b2f6-4b07-8bdf-46235a97238e",
              "name": "Bad request.",
              "originalRequest": {
                "url": {
                  "path": [
                    "organization_exports",
                    ":organization_export_gid"
                  ],
                  "host": [
                    "{{baseUrl}}"
                  ],
                  "query": [],
                  "variable": [
                    {
                      "disabled": false,
                      "type": "any",
                      "value": "<string>",
                      "key": "organization_export_gid",
                      "description": "(Required) "
                    }
                  ]
                },
                "header": [
                  {
                    "description": {
                      "content": "Added as a part of security scheme: bearer",
                      "type": "text/plain"
                    },
                    "key": "Authorization",
                    "value": "Bearer <token>"
                  }
                ],
                "method": "GET",
                "body": {}
              },
              "status": "Bad Request",
              "code": 400,
              "header": [
                {
                  "key": "Content-Type",
                  "value": "text/plain"
                }
              ],
              "body": "",
              "cookie": [],
              "_postman_previewlanguage": "text"
            },
            {
              "id": "af9c29c6-54ee-4484-b570-6c102c5bb639",
              "name": "Unauthorized.",
              "originalRequest": {
                "url": {
                  "path": [
                    "organization_exports",
                    ":organization_export_gid"
                  ],
                  "host": [
                    "{{baseUrl}}"
                  ],
                  "query": [],
                  "variable": [
                    {
                      "disabled": false,
                      "type": "any",
                      "value": "<string>",
                      "key": "organization_export_gid",
                      "description": "(Required) "
                    }
                  ]
                },
                "header": [
                  {
                    "description": {
                      "content": "Added as a part of security scheme: bearer",
                      "type": "text/plain"
                    },
                    "key": "Authorization",
                    "value": "Bearer <token>"
                  }
                ],
                "method": "GET",
                "body": {}
              },
              "status": "Unauthorized",
              "code": 401,
              "header": [
                {
                  "key": "Content-Type",
                  "value": "text/plain"
                }
              ],
              "body": "",
              "cookie": [],
              "_postman_previewlanguage": "text"
            },
            {
              "id": "24256737-cec9-41af-a0d1-a9fef7f76a35",
              "name": "Forbidden.",
              "originalRequest": {
                "url": {
                  "path": [
                    "organization_exports",
                    ":organization_export_gid"
                  ],
                  "host": [
                    "{{baseUrl}}"
                  ],
                  "query": [],
                  "variable": [
                    {
                      "disabled": false,
                      "type": "any",
                      "value": "<string>",
                      "key": "organization_export_gid",
                      "description": "(Required) "
                    }
                  ]
                },
                "header": [
                  {
                    "description": {
                      "content": "Added as a part of security scheme: bearer",
                      "type": "text/plain"
                    },
                    "key": "Authorization",
                    "value": "Bearer <token>"
                  }
                ],
                "method": "GET",
                "body": {}
              },
              "status": "Forbidden",
              "code": 403,
              "header": [
                {
                  "key": "Content-Type",
                  "value": "text/plain"
                }
              ],
              "body": "",
              "cookie": [],
              "_postman_previewlanguage": "text"
            },
            {
              "id": "912f69ae-ba37-45b8-aa93-2b33b31aeb61",
              "name": "Not found.",
              "originalRequest": {
                "url": {
                  "path": [
                    "organization_exports",
                    ":organization_export_gid"
                  ],
                  "host": [
                    "{{baseUrl}}"
                  ],
                  "query": [],
                  "variable": [
                    {
                      "disabled": false,
                      "type": "any",
                      "value": "<string>",
                      "key": "organization_export_gid",
                      "description": "(Required) "
                    }
                  ]
                },
                "header": [
                  {
                    "description": {
                      "content": "Added as a part of security scheme: bearer",
                      "type": "text/plain"
                    },
                    "key": "Authorization",
                    "value": "Bearer <token>"
                  }
                ],
                "method": "GET",
                "body": {}
              },
              "status": "Not Found",
              "code": 404,
              "header": [
                {
                  "key": "Content-Type",
                  "value": "text/plain"
                }
              ],
              "body": "",
              "cookie": [],
              "_postman_previewlanguage": "text"
            },
            {
              "id": "f0746327-540d-410f-a5b5-b6d5dc8dd8e0",
              "name": "Internal server error.",
              "originalRequest": {
                "url": {
                  "path": [
                    "organization_exports",
                    ":organization_export_gid"
                  ],
                  "host": [
                    "{{baseUrl}}"
                  ],
                  "query": [],
                  "variable": [
                    {
                      "disabled": false,
                      "type": "any",
                      "value": "<string>",
                      "key": "organization_export_gid",
                      "description": "(Required) "
                    }
                  ]
                },
                "header": [
                  {
                    "description": {
                      "content": "Added as a part of security scheme: bearer",
                      "type": "text/plain"
                    },
                    "key": "Authorization",
                    "value": "Bearer <token>"
                  }
                ],
                "method": "GET",
                "body": {}
              },
              "status": "Internal Server Error",
              "code": 500,
              "header": [
                {
                  "key": "Content-Type",
                  "value": "text/plain"
                }
              ],
              "body": "",
              "cookie": [],
              "_postman_previewlanguage": "text"
            }
          ],
          "event": [],
          "protocolProfileBehavior": {
            "disableBodyPruning": true
          }
        }
      ],
      "event": []
    }
  ],
  "event": [],
  "variable": [
    {
      "type": "string",
      "value": "https://app.asana.com/api/1.0",
      "key": "baseUrl"
    }
  ],
  "auth": {
    "type": "bearer",
    "bearer": [
      {
        "key": "token",
        "value": "{{bearerToken}}"
      }
    ]
  },
  "info": {
    "_postman_id": "b1a95fd8-f928-4211-8d50-b2f868295353",
    "name": "Asana Organization Exports API",
    "schema": "https://schema.getpostman.com/json/collection/v2.1.0/collection.json",
    "description": {
      "content": "The Asana Organization Exports API allows users to export the complete data of an organization in JSON format. Only available to Service Accounts of Enterprise organizations.\n\nContact Support:\n Name: Asana Support",
      "type": "text/plain"
    }
  }
}